vevestaX/__init__.py
vevestaX/vevesta.py
vevestaX-6.8.5.dist-info/LICENSE
vevestaX-6.8.5.dist-info/METADATA
vevestaX-6.8.5.dist-info/WHEEL
vevestaX-6.8.5.dist-info/top_level.txt
vevestaX-6.8.5.dist-info/RECORD
